README.md
setup.py
sanic_cookies/__init__.py
sanic_cookies/models.py
sanic_cookies.egg-info/PKG-INFO
sanic_cookies.egg-info/SOURCES.txt
sanic_cookies.egg-info/dependency_links.txt
sanic_cookies.egg-info/requires.txt
sanic_cookies.egg-info/top_level.txt
sanic_cookies/interfaces/__init__.py
sanic_cookies/interfaces/aioredis.py
sanic_cookies/interfaces/gino_asyncpg.py
sanic_cookies/interfaces/incookie.py
sanic_cookies/interfaces/inmemory.py
sanic_cookies/sessions/__init__.py
sanic_cookies/sessions/auth.py
sanic_cookies/sessions/base.py
tests/__init__.py
tests/common.py
tests/test_auth_session.py
tests/test_base_session.py
tests/test_incookie.py
tests/test_inmemory.py
tests/test_session_dict.py
tests/test_synchronization.py