Metadata-Version: 2.1
Name: sanic-cookies
Version: 0.4.1
Summary: Sanic Cookie and Session Management
Home-page: https://github.com/omarryhan/sanic-cookies
Author: Omar Ryhan
Author-email: omarryhan@gmail.com
License: GNU
Platform: UNKNOWN
Classifier: Programming Language :: Python :: 3.7
Classifier: Operating System :: OS Independent
